nidhoggr/application.py
nidhoggr/errors/__init__.py
nidhoggr/errors/auth.py
nidhoggr/errors/common.py
nidhoggr/errors/session.py
nidhoggr/models/__init__.py
nidhoggr/models/auth.py
nidhoggr/models/session.py
nidhoggr/utils/__init__.py
nidhoggr/utils/crypto.py
nidhoggr/utils/decorator.py
nidhoggr/utils/repository.py
nidhoggr/utils/transformer.py
nidhoggr/views/__init__.py
nidhoggr/views/auth.py
nidhoggr/views/core.py
nidhoggr/views/session.py
tests/__init__.py
tests/conftest.py
tests/auth/__init__.py
tests/auth/conftest.py
tests/auth/test_authenticate.py
tests/auth/test_basic.py
tests/auth/test_invalidate.py
tests/auth/test_refresh.py
tests/auth/test_signout.py
tests/auth/test_validate.py
tests/data/users.json
tests/session/__init__.py
tests/session/conftest.py
tests/session/test_crypto.py
tests/session/test_has_joined.py
tests/session/test_join.py
tests/session/test_profile.py
tests/texture/__init__.py
nidhoggr-1.0.1.dist-info/LICENSE
nidhoggr-1.0.1.dist-info/METADATA
nidhoggr-1.0.1.dist-info/WHEEL
nidhoggr-1.0.1.dist-info/top_level.txt
nidhoggr-1.0.1.dist-info/RECORD
