Metadata-Version: 2.1
Name: nidhoggr
Version: 1.0.1
Summary: Yggdrasil protocol implementation
Home-page: https://git.mc4ep.org/mc4ep/nidhoggr
Author: Andriy Kushnir (Orhideous)
Author-email: me@orhideous.name
License: MIT
Keywords: Minecraft,Yggdrasil,Authentication
Platform: UNKNOWN
Classifier: Development Status :: 4 - Beta
Classifier: Environment :: No Input/Output (Daemon)
Classifier: Framework :: Flask
Classifier: Intended Audience :: Developers
Classifier: Intended Audience :: System Administrators
Classifier: License :: OSI Approved
Classifier: License :: OSI Approved :: MIT License
Classifier: Operating System :: OS Independent
Classifier: Programming Language :: Python
Classifier: Programming Language :: Python :: 3
Classifier: Programming Language :: Python :: 3.6
Classifier: Programming Language :: Python :: 3.7
Classifier: Programming Language :: Python :: Implementation :: CPython
Classifier: Programming Language :: Python :: Implementation :: PyPy
Classifier: Topic :: Internet :: WWW/HTTP :: WSGI
Classifier: Topic :: Internet :: WWW/HTTP :: WSGI :: Application
Classifier: Topic :: Utilities
Requires-Dist: Flask (>=1.1)
Requires-Dist: nidhoggr-core (>=0.11.1)
Requires-Dist: pydantic (>=1.7)
Requires-Dist: M2Crypto (>=0.35)
